streamlit_extented/__init__.py
streamlit_extented/core.py
streamlit_extented-0.1.0.dist-info/LICENSE
streamlit_extented-0.1.0.dist-info/METADATA
streamlit_extented-0.1.0.dist-info/WHEEL
streamlit_extented-0.1.0.dist-info/top_level.txt
streamlit_extented-0.1.0.dist-info/RECORD
