Metadata-Version: 2.2
Name: streamlit-extented
Version: 0.1.0
Summary: Расширение для работы с базами данных через pyodbc с поддержкой JSON
Author: Voronov Andrey
Classifier: Programming Language :: Python :: 3.8
Classifier: License :: OSI Approved :: MIT License
Classifier: Operating System :: OS Independent
Requires-Python: >=3.7
License-File: LICENSE
Requires-Dist: pyodbc
Dynamic: author
Dynamic: classifier
Dynamic: description
Dynamic: description-content-type
Dynamic: requires-dist
Dynamic: requires-python
Dynamic: summary
